[
 {
  "id": "87ecae95-e662-4f8d-82e0-27dd1669d3a2",
  "escopo": "area",
  "id_area": "regulares",
  "id_curso": null,
  "id_turma": null,
  "id_pergunta": "b19ec6b3-2299-40ec-8e71-8d89536f797a",
  "obrigatorio": true,
  "observacoes": null,
  "tipo_processo": "matricula",
  "bloco": "dados_pessoais",
  "ordem": 15,
  "leitura": false,
  "tipo_candidatura": "estudante",
  "largura_coluna": "simples",
  "altura_coluna": "simples",
  "largura": 2,
  "altura": 36,
  "depende": false,
  "depende_de": null,
  "valor_depende": null,
  "pergunta_gatilho": false,
  "valor_gatilho": null,
  "ordem_bloco": 1
 },
 {
  "id": "92cf945e-3625-46c5-91ee-566d9fe595a8",
  "escopo": "area",
  "id_area": "regulares",
  "id_curso": null,
  "id_turma": null,
  "id_pergunta": "2f53dcc3-4429-457c-bcb1-6487bc3ab5af",
  "obrigatorio": true,
  "observacoes": null,
  "tipo_processo": "matricula",
  "bloco": "dados_pessoais",
  "ordem": 9,
  "leitura": false,
  "tipo_candidatura": "estudante",
  "largura_coluna": "simples",
  "altura_coluna": "simples",
  "largura": 1,
  "altura": 36,
  "depende": false,
  "depende_de": null,
  "valor_depende": null,
  "pergunta_gatilho": false,
  "valor_gatilho": null,
  "ordem_bloco": 1
 },
 {
  "id": "428360aa-b3c7-4d1a-a69c-ecc4d3483e96",
  "escopo": "area",
  "id_area": "regulares",
  "id_curso": null,
  "id_turma": null,
  "id_pergunta": "5747a06b-2385-4920-af8a-48f8ec870518",
  "obrigatorio": true,
  "observacoes": null,
  "tipo_processo": "matricula",
  "bloco": "dados_pessoais",
  "ordem": 4,
  "leitura": false,
  "tipo_candidatura": "estudante",
  "largura_coluna": "dupla",
  "altura_coluna": "simples",
  "largura": 2,
  "altura": 36,
  "depende": false,
  "depende_de": null,
  "valor_depende": null,
  "pergunta_gatilho": false,
  "valor_gatilho": null,
  "ordem_bloco": 1
 },
 {
  "id": "aedf2b42-cc45-4f3f-9158-c2f6a687927a",
  "escopo": "area",
  "id_area": "regulares",
  "id_curso": null,
  "id_turma": null,
  "id_pergunta": "289e962e-da61-4cf3-9810-7ece9de8f19f",
  "obrigatorio": true,
  "observacoes": null,
  "tipo_processo": "matricula",
  "bloco": "dados_pessoais",
  "ordem": 13,
  "leitura": false,
  "tipo_candidatura": "estudante",
  "largura_coluna": "dupla",
  "altura_coluna": "simples",
  "largura": 1,
  "altura": 36,
  "depende": false,
  "depende_de": null,
  "valor_depende": null,
  "pergunta_gatilho": false,
  "valor_gatilho": null,
  "ordem_bloco": 1
 },
 {
  "id": "5d9f12bd-7dd5-4b2e-8fa5-6c58f0514941",
  "escopo": "area",
  "id_area": "regulares",
  "id_curso": null,
  "id_turma": null,
  "id_pergunta": "d42f73a8-0a61-4f6a-acd1-767b06bd612e",
  "obrigatorio": true,
  "observacoes": null,
  "tipo_processo": "matricula",
  "bloco": "dados_pessoais",
  "ordem": 10,
  "leitura": false,
  "tipo_candidatura": "estudante",
  "largura_coluna": "dupla",
  "altura_coluna": "simples",
  "largura": 2,
  "altura": 36,
  "depende": false,
  "depende_de": null,
  "valor_depende": null,
  "pergunta_gatilho": false,
  "valor_gatilho": null,
  "ordem_bloco": 1
 },
 {
  "id": "3ceb4319-4c90-4cbb-8431-8c22e6c8655e",
  "escopo": "area",
  "id_area": "regulares",
  "id_curso": null,
  "id_turma": null,
  "id_pergunta": "c95e476a-c4dc-4520-badd-d7392b0aeab7",
  "obrigatorio": true,
  "observacoes": null,
  "tipo_processo": "matricula",
  "bloco": "dados_pessoais",
  "ordem": 11,
  "leitura": false,
  "tipo_candidatura": "estudante",
  "largura_coluna": "dupla",
  "altura_coluna": "simples",
  "largura": 2,
  "altura": 36,
  "depende": false,
  "depende_de": null,
  "valor_depende": null,
  "pergunta_gatilho": false,
  "valor_gatilho": null,
  "ordem_bloco": 1
 },
 {
  "id": "9403fb1f-4364-4f04-85d9-2d708fd4e18b",
  "escopo": "area",
  "id_area": "regulares",
  "id_curso": null,
  "id_turma": null,
  "id_pergunta": "895e1782-ae13-4027-a356-d1800f4297e4",
  "obrigatorio": true,
  "observacoes": null,
  "tipo_processo": "matricula",
  "bloco": "dados_pessoais",
  "ordem": 12,
  "leitura": false,
  "tipo_candidatura": "estudante",
  "largura_coluna": "dupla",
  "altura_coluna": "simples",
  "largura": 2,
  "altura": 36,
  "depende": false,
  "depende_de": null,
  "valor_depende": null,
  "pergunta_gatilho": false,
  "valor_gatilho": null,
  "ordem_bloco": 1
 },
 {
  "id": "816c1acf-c48b-4854-b89d-0e1cab801f23",
  "escopo": "area",
  "id_area": "regulares",
  "id_curso": null,
  "id_turma": null,
  "id_pergunta": "93642773-5a9c-4ada-8356-21e7e7bb9eda",
  "obrigatorio": true,
  "observacoes": null,
  "tipo_processo": "matricula",
  "bloco": "dados_pessoais",
  "ordem": 8,
  "leitura": false,
  "tipo_candidatura": "estudante",
  "largura_coluna": "simples",
  "altura_coluna": "simples",
  "largura": 1,
  "altura": 36,
  "depende": false,
  "depende_de": null,
  "valor_depende": null,
  "pergunta_gatilho": false,
  "valor_gatilho": null,
  "ordem_bloco": 1
 },
 {
  "id": "3a548c68-22aa-4c8c-85e8-f65c0e141b7d",
  "escopo": "area",
  "id_area": "regulares",
  "id_curso": null,
  "id_turma": null,
  "id_pergunta": "78e5931f-9f8f-4f9b-bbb0-36041c404c4e",
  "obrigatorio": true,
  "observacoes": null,
  "tipo_processo": "matricula",
  "bloco": "dados_pessoais",
  "ordem": 5,
  "leitura": false,
  "tipo_candidatura": "estudante",
  "largura_coluna": "dupla",
  "altura_coluna": "alta",
  "largura": 2,
  "altura": 120,
  "depende": false,
  "depende_de": null,
  "valor_depende": null,
  "pergunta_gatilho": false,
  "valor_gatilho": null,
  "ordem_bloco": 1
 },
 {
  "id": "34e50fdf-6b67-415d-bdb9-932928f2d13b",
  "escopo": "area",
  "id_area": "regulares",
  "id_curso": null,
  "id_turma": null,
  "id_pergunta": "8925bdc2-538a-408d-bd34-fb64b2638621",
  "obrigatorio": true,
  "observacoes": null,
  "tipo_processo": "matricula",
  "bloco": "dados_pessoais",
  "ordem": 6,
  "leitura": false,
  "tipo_candidatura": "estudante",
  "largura_coluna": "simples",
  "altura_coluna": "simples",
  "largura": 1,
  "altura": 36,
  "depende": false,
  "depende_de": null,
  "valor_depende": null,
  "pergunta_gatilho": false,
  "valor_gatilho": null,
  "ordem_bloco": 1
 },
 {
  "id": "18601899-2e7f-439c-a3f2-f45e6dc36383",
  "escopo": "area",
  "id_area": "regulares",
  "id_curso": null,
  "id_turma": null,
  "id_pergunta": "57ea34cf-27ed-460d-b27c-244f49d36d62",
  "obrigatorio": true,
  "observacoes": null,
  "tipo_processo": "matricula",
  "bloco": "dados_pessoais",
  "ordem": 7,
  "leitura": false,
  "tipo_candidatura": "estudante",
  "largura_coluna": "simples",
  "altura_coluna": "simples",
  "largura": 1,
  "altura": 36,
  "depende": false,
  "depende_de": null,
  "valor_depende": null,
  "pergunta_gatilho": false,
  "valor_gatilho": null,
  "ordem_bloco": 1
 },
 {
  "id": "6e71a301-a3c0-423e-9c0d-9e729052d8a6",
  "escopo": "area",
  "id_area": "regulares",
  "id_curso": null,
  "id_turma": null,
  "id_pergunta": "74545877-be62-49e1-8354-8fd004c57a61",
  "obrigatorio": true,
  "observacoes": null,
  "tipo_processo": "matricula",
  "bloco": "dados_pessoais",
  "ordem": 14,
  "leitura": false,
  "tipo_candidatura": "estudante",
  "largura_coluna": "simples",
  "altura_coluna": "simples",
  "largura": 1,
  "altura": 36,
  "depende": false,
  "depende_de": null,
  "valor_depende": null,
  "pergunta_gatilho": false,
  "valor_gatilho": null,
  "ordem_bloco": 1
 }
]